nonebot_plugin_llm_helper/__init__.py
nonebot_plugin_llm_helper/config.py
nonebot_plugin_llm_helper/data.py
nonebot_plugin_llm_helper/generate.py
nonebot_plugin_llm_helper/network.py
nonebot_plugin_llm_helper/plugin.py
nonebot_plugin_llm_helper/prompt.txt
nonebot_plugin_llm_helper/utils.py
nonebot_plugin_llm_helper-0.0.3.dist-info/LICENSE
nonebot_plugin_llm_helper-0.0.3.dist-info/METADATA
nonebot_plugin_llm_helper-0.0.3.dist-info/WHEEL
nonebot_plugin_llm_helper-0.0.3.dist-info/RECORD
