Metadata-Version: 2.3
Name: nonebot-plugin-llm-helper
Version: 0.0.3
Summary: 一个支持多平台的帮助插件，基于 LLM 解析 Github 仓库或代码。
License: GPL3
Keywords: nonebot,nonebot2,helper,llm,ai
Author: Lonely-Sails
Requires-Python: >=3.8,<4.0
Classifier: License :: Other/Proprietary License
Classifier: Programming Language :: Python :: 3
Classifier: Programming Language :: Python :: 3.8
Classifier: Programming Language :: Python :: 3.9
Classifier: Programming Language :: Python :: 3.10
Classifier: Programming Language :: Python :: 3.11
Classifier: Programming Language :: Python :: 3.12
Classifier: Programming Language :: Python :: 3.13
Requires-Dist: httpx (>=0.20.0,<0.21.0)
Requires-Dist: nonebot-plugin-alconna (>=0.59.0,<0.60.0)
Requires-Dist: nonebot-plugin-localstore (>=0.7.0,<0.8.0)
Requires-Dist: nonebot2 (>=2.2.0,<3.0.0)
Requires-Dist: pydantic (>=1.0.0,<2.0.0)
Project-URL: Documentation, https://github.com/Lonely-Sails/nonebot-plugin-llm-helper#readme
Project-URL: Homepage, https://github.com/Lonely-Sails/nonebot-plugin-llm-helper
Project-URL: Repository, https://github.com/Lonely-Sails/nonebot-plugin-llm-helper
